[
  {
    "ContainingType": "support.server.Controllers.AuthController",
    "Method": "Login",
    "RelativePath": "api/Auth/login",
    "HttpMethod": "POST",
    "IsController": true,
    "Order": 0,
    "Parameters": [
      {
        "Name": "user",
        "Type": "support.server.DTOs.UserDto",
        "IsRequired": true
      }
    ],
    "ReturnTypes": [
      {
        "Type": "support.server.Models.TicketLog",
        "MediaTypes": [
          "text/plain",
          "application/json",
          "text/json"
        ],
        "StatusCode": 200
      }
    ]
  },
  {
    "ContainingType": "support.server.Controllers.NotificationController",
    "Method": "Send",
    "RelativePath": "api/Notification/send",
    "HttpMethod": "POST",
    "IsController": true,
    "Order": 0,
    "Parameters": [
      {
        "Name": "payload",
        "Type": "System.Object",
        "IsRequired": true
      }
    ],
    "ReturnTypes": []
  },
  {
    "ContainingType": "support.server.Controllers.PermissionsController",
    "Method": "GetAll",
    "RelativePath": "api/Permissions",
    "HttpMethod": "GET",
    "IsController": true,
    "Order": 0,
    "Parameters": [],
    "ReturnTypes": [
      {
        "Type": "System.Collections.Generic.IEnumerable\u00601[[support.server.Models.Permision, support.server, Version=1.0.0.0, Culture=neutral, PublicKeyToken=null]]",
        "MediaTypes": [
          "text/plain",
          "application/json",
          "text/json"
        ],
        "StatusCode": 200
      }
    ]
  },
  {
    "ContainingType": "support.server.Controllers.PermissionsController",
    "Method": "Create",
    "RelativePath": "api/Permissions",
    "HttpMethod": "POST",
    "IsController": true,
    "Order": 0,
    "Parameters": [
      {
        "Name": "model",
        "Type": "support.server.Models.Permision",
        "IsRequired": true
      }
    ],
    "ReturnTypes": [
      {
        "Type": "support.server.Models.Permision",
        "MediaTypes": [
          "text/plain",
          "application/json",
          "text/json"
        ],
        "StatusCode": 200
      }
    ]
  },
  {
    "ContainingType": "support.server.Controllers.PermissionsController",
    "Method": "GetByCode",
    "RelativePath": "api/Permissions/{code}",
    "HttpMethod": "GET",
    "IsController": true,
    "Order": 0,
    "Parameters": [
      {
        "Name": "code",
        "Type": "System.String",
        "IsRequired": true
      }
    ],
    "ReturnTypes": [
      {
        "Type": "support.server.Models.Permision",
        "MediaTypes": [
          "text/plain",
          "application/json",
          "text/json"
        ],
        "StatusCode": 200
      }
    ]
  },
  {
    "ContainingType": "support.server.Controllers.PermissionsController",
    "Method": "Update",
    "RelativePath": "api/Permissions/{code}",
    "HttpMethod": "PUT",
    "IsController": true,
    "Order": 0,
    "Parameters": [
      {
        "Name": "code",
        "Type": "System.String",
        "IsRequired": true
      },
      {
        "Name": "model",
        "Type": "support.server.Models.Permision",
        "IsRequired": true
      }
    ],
    "ReturnTypes": []
  },
  {
    "ContainingType": "support.server.Controllers.PermissionsController",
    "Method": "Delete",
    "RelativePath": "api/Permissions/{code}",
    "HttpMethod": "DELETE",
    "IsController": true,
    "Order": 0,
    "Parameters": [
      {
        "Name": "code",
        "Type": "System.String",
        "IsRequired": true
      }
    ],
    "ReturnTypes": []
  },
  {
    "ContainingType": "support.server.Controllers.TicketLogsController",
    "Method": "GetPagedList",
    "RelativePath": "api/TicketLogs",
    "HttpMethod": "GET",
    "IsController": true,
    "Order": 0,
    "Parameters": [
      {
        "Name": "page",
        "Type": "System.Int32",
        "IsRequired": false
      },
      {
        "Name": "pageSize",
        "Type": "System.Int32",
        "IsRequired": false
      },
      {
        "Name": "status",
        "Type": "System.Nullable\u00601[[System.Byte, System.Private.CoreLib, Version=8.0.0.0, Culture=neutral, PublicKeyToken=7cec85d7bea7798e]]",
        "IsRequired": false
      },
      {
        "Name": "department",
        "Type": "System.String",
        "IsRequired": false
      },
      {
        "Name": "keyword",
        "Type": "System.String",
        "IsRequired": false
      },
      {
        "Name": "usercode",
        "Type": "System.String",
        "IsRequired": false
      },
      {
        "Name": "fromDate",
        "Type": "System.Nullable\u00601[[System.DateTime, System.Private.CoreLib, Version=8.0.0.0, Culture=neutral, PublicKeyToken=7cec85d7bea7798e]]",
        "IsRequired": false
      },
      {
        "Name": "toDate",
        "Type": "System.Nullable\u00601[[System.DateTime, System.Private.CoreLib, Version=8.0.0.0, Culture=neutral, PublicKeyToken=7cec85d7bea7798e]]",
        "IsRequired": false
      }
    ],
    "ReturnTypes": []
  },
  {
    "ContainingType": "support.server.Controllers.TicketLogsController",
    "Method": "GetById",
    "RelativePath": "api/TicketLogs/{id}",
    "HttpMethod": "GET",
    "IsController": true,
    "Order": 0,
    "Parameters": [
      {
        "Name": "id",
        "Type": "System.Int32",
        "IsRequired": true
      }
    ],
    "ReturnTypes": [
      {
        "Type": "support.server.Models.TicketLog",
        "MediaTypes": [
          "text/plain",
          "application/json",
          "text/json"
        ],
        "StatusCode": 200
      }
    ]
  },
  {
    "ContainingType": "support.server.Controllers.TicketLogsController",
    "Method": "Delete",
    "RelativePath": "api/TicketLogs/{id}",
    "HttpMethod": "DELETE",
    "IsController": true,
    "Order": 0,
    "Parameters": [
      {
        "Name": "id",
        "Type": "System.Int32",
        "IsRequired": true
      }
    ],
    "ReturnTypes": []
  },
  {
    "ContainingType": "support.server.Controllers.TicketLogsController",
    "Method": "UpdateCompleted",
    "RelativePath": "api/TicketLogs/completed/{id}",
    "HttpMethod": "PUT",
    "IsController": true,
    "Order": 0,
    "Parameters": [
      {
        "Name": "id",
        "Type": "System.Int32",
        "IsRequired": true
      },
      {
        "Name": "model",
        "Type": "support.server.Models.TicketLog",
        "IsRequired": true
      }
    ],
    "ReturnTypes": []
  },
  {
    "ContainingType": "support.server.Controllers.TicketLogsController",
    "Method": "Create",
    "RelativePath": "api/TicketLogs/create",
    "HttpMethod": "POST",
    "IsController": true,
    "Order": 0,
    "Parameters": [
      {
        "Name": "TicketId",
        "Type": "System.Int32",
        "IsRequired": false
      },
      {
        "Name": "TicketCode",
        "Type": "System.String",
        "IsRequired": false
      },
      {
        "Name": "TicketTitle",
        "Type": "System.String",
        "IsRequired": false
      },
      {
        "Name": "TicketType",
        "Type": "System.String",
        "IsRequired": false
      },
      {
        "Name": "TicketContent",
        "Type": "System.String",
        "IsRequired": false
      },
      {
        "Name": "TicketStatus",
        "Type": "System.Nullable\u00601[[System.Byte, System.Private.CoreLib, Version=8.0.0.0, Culture=neutral, PublicKeyToken=7cec85d7bea7798e]]",
        "IsRequired": false
      },
      {
        "Name": "FileAttachments",
        "Type": "System.String",
        "IsRequired": false
      },
      {
        "Name": "UploadedFile",
        "Type": "Microsoft.AspNetCore.Http.IFormFile",
        "IsRequired": false
      },
      {
        "Name": "CreatedAt",
        "Type": "System.Nullable\u00601[[System.DateTime, System.Private.CoreLib, Version=8.0.0.0, Culture=neutral, PublicKeyToken=7cec85d7bea7798e]]",
        "IsRequired": false
      },
      {
        "Name": "ReceivedAt",
        "Type": "System.Nullable\u00601[[System.DateTime, System.Private.CoreLib, Version=8.0.0.0, Culture=neutral, PublicKeyToken=7cec85d7bea7798e]]",
        "IsRequired": false
      },
      {
        "Name": "UserCode",
        "Type": "System.String",
        "IsRequired": false
      },
      {
        "Name": "UserName",
        "Type": "System.String",
        "IsRequired": false
      },
      {
        "Name": "UserDepartment",
        "Type": "System.String",
        "IsRequired": false
      },
      {
        "Name": "UserContact",
        "Type": "System.String",
        "IsRequired": false
      },
      {
        "Name": "UserAssigneeCode",
        "Type": "System.String",
        "IsRequired": false
      },
      {
        "Name": "UserAssigneeName",
        "Type": "System.String",
        "IsRequired": false
      },
      {
        "Name": "UserAssigneeDepartment",
        "Type": "System.String",
        "IsRequired": false
      },
      {
        "Name": "ApprovedAt",
        "Type": "System.Nullable\u00601[[System.DateTime, System.Private.CoreLib, Version=8.0.0.0, Culture=neutral, PublicKeyToken=7cec85d7bea7798e]]",
        "IsRequired": false
      },
      {
        "Name": "Note",
        "Type": "System.String",
        "IsRequired": false
      }
    ],
    "ReturnTypes": [
      {
        "Type": "support.server.Models.TicketLog",
        "MediaTypes": [
          "text/plain",
          "application/json",
          "text/json"
        ],
        "StatusCode": 200
      }
    ]
  },
  {
    "ContainingType": "support.server.Controllers.TicketLogsController",
    "Method": "Update",
    "RelativePath": "api/TicketLogs/received/{id}",
    "HttpMethod": "PUT",
    "IsController": true,
    "Order": 0,
    "Parameters": [
      {
        "Name": "id",
        "Type": "System.Int32",
        "IsRequired": true
      },
      {
        "Name": "model",
        "Type": "support.server.Models.TicketLog",
        "IsRequired": true
      }
    ],
    "ReturnTypes": []
  },
  {
    "ContainingType": "support.server.Controllers.TicketLogsController",
    "Method": "UpdateReset",
    "RelativePath": "api/TicketLogs/reset/{id}",
    "HttpMethod": "PUT",
    "IsController": true,
    "Order": 0,
    "Parameters": [
      {
        "Name": "id",
        "Type": "System.Int32",
        "IsRequired": true
      },
      {
        "Name": "model",
        "Type": "support.server.Models.TicketLog",
        "IsRequired": true
      }
    ],
    "ReturnTypes": []
  },
  {
    "ContainingType": "support.server.Controllers.UploadsController",
    "Method": "UploadImage",
    "RelativePath": "api/Uploads/image",
    "HttpMethod": "POST",
    "IsController": true,
    "Order": 0,
    "Parameters": [
      {
        "Name": "file",
        "Type": "Microsoft.AspNetCore.Http.IFormFile",
        "IsRequired": false
      }
    ],
    "ReturnTypes": []
  },
  {
    "ContainingType": "support.server.Controllers.UserPermissionsController",
    "Method": "GetAll",
    "RelativePath": "api/UserPermissions",
    "HttpMethod": "GET",
    "IsController": true,
    "Order": 0,
    "Parameters": [],
    "ReturnTypes": [
      {
        "Type": "System.Collections.Generic.IEnumerable\u00601[[support.server.Models.UserPermission, support.server, Version=1.0.0.0, Culture=neutral, PublicKeyToken=null]]",
        "MediaTypes": [
          "text/plain",
          "application/json",
          "text/json"
        ],
        "StatusCode": 200
      }
    ]
  },
  {
    "ContainingType": "support.server.Controllers.UserPermissionsController",
    "Method": "Create",
    "RelativePath": "api/UserPermissions",
    "HttpMethod": "POST",
    "IsController": true,
    "Order": 0,
    "Parameters": [
      {
        "Name": "model",
        "Type": "support.server.Models.UserPermission",
        "IsRequired": true
      }
    ],
    "ReturnTypes": []
  },
  {
    "ContainingType": "support.server.Controllers.UserPermissionsController",
    "Method": "Update",
    "RelativePath": "api/UserPermissions/{id}",
    "HttpMethod": "PUT",
    "IsController": true,
    "Order": 0,
    "Parameters": [
      {
        "Name": "id",
        "Type": "System.Int32",
        "IsRequired": true
      },
      {
        "Name": "model",
        "Type": "support.server.Models.UserPermission",
        "IsRequired": true
      }
    ],
    "ReturnTypes": []
  },
  {
    "ContainingType": "support.server.Controllers.UserPermissionsController",
    "Method": "Delete",
    "RelativePath": "api/UserPermissions/{id}",
    "HttpMethod": "DELETE",
    "IsController": true,
    "Order": 0,
    "Parameters": [
      {
        "Name": "id",
        "Type": "System.Int32",
        "IsRequired": true
      }
    ],
    "ReturnTypes": []
  },
  {
    "ContainingType": "support.server.Controllers.UserPermissionsController",
    "Method": "GetById",
    "RelativePath": "api/UserPermissions/{MaNV}",
    "HttpMethod": "GET",
    "IsController": true,
    "Order": 0,
    "Parameters": [
      {
        "Name": "MaNV",
        "Type": "System.String",
        "IsRequired": true
      }
    ],
    "ReturnTypes": [
      {
        "Type": "support.server.Models.UserPermission",
        "MediaTypes": [
          "text/plain",
          "application/json",
          "text/json"
        ],
        "StatusCode": 200
      }
    ]
  }
]